swimlane_utils/__init__.py
swimlane_utils/flattener.py
swimlane_utils/rest.py
swimlane_utils-0.0.4.dist-info/METADATA
swimlane_utils-0.0.4.dist-info/RECORD
swimlane_utils-0.0.4.dist-info/WHEEL
swimlane_utils-0.0.4.dist-info/top_level.txt
