Metadata-Version: 2.1
Name: swimlane-utils
Version: 0.0.4
Summary: Swimlane Utilities Package
Home-page: UNKNOWN
Author: Swimlane
Author-email: info@swimlane.com
License: UNKNOWN
Keywords: utilities,dictionary,flattening,rest
Platform: UNKNOWN
Requires-Dist: requests (<3,>=2)
